pygenuz/__init__.py
pygenuz/app.py
pygenuz/configs.py
pygenuz/db.py
pygenuz/middelware.py
pygenuz/response.py
pygenuz-0.3.0.dist-info/METADATA
pygenuz-0.3.0.dist-info/WHEEL
pygenuz-0.3.0.dist-info/top_level.txt
pygenuz-0.3.0.dist-info/RECORD
